[
    {
        "Picture": "/berries/cheri.png",
        "Name": "Cheri Berry",
        "Firmness": "Soft",
        "Description": "This bright red Berry is very spicy and has a provocative flavor. It blooms with delicate, pretty flowers.",
        "Spicy": 10,
        "Dry": 0,
        "Sweet": 0,
        "Bitter": 0,
        "Sour": 0,
        "Smoothness": 25
    },
    {
        "Picture": "/berries/chesto.png",
        "Name": "Chesto Berry",
        "Firmness": "Super Hard",
        "Description": "This Berry's thick skin and fruit are very tough and dry-tasting. However, every bit of it can be eaten.",
        "Spicy": 0,
        "Dry": 10,
        "Sweet": 0,
        "Bitter": 0,
        "Sour": 0,
        "Smoothness": 25
    },
    {
        "Picture": "/berries/pecha.png",
        "Name": "Pecha Berry",
        "Firmness": "Very Soft",
        "Description": "Because of its hollow inside pocket, there isn't a lot to eat. What can be eaten is very sweet and delicious.",
        "Spicy": 0,
        "Dry": 0,
        "Sweet": 10,
        "Bitter": 0,
        "Sour": 0,
        "Smoothness": 25
    },
    {
        "Picture": "/berries/rawst.png",
        "Name": "Rawst Berry",
        "Firmness": "Hard",
        "Description": "If the leaves grow longer and curlier than average, this Berry will have a somewhat bitter taste.",
        "Spicy": 0,
        "Dry": 0,
        "Sweet": 0,
        "Bitter": 10,
        "Sour": 0,
        "Smoothness": 25
    },
    {
        "Picture": "/berries/aspear.png",
        "Name": "Aspear Berry",
        "Firmness": "Super Hard",
        "Description": "This Berry's peel is hard, but the flesh inside is very juicy. It is distinguished by its bracing sourness.",
        "Spicy": 0,
        "Dry": 0,
        "Sweet": 0,
        "Bitter": 0,
        "Sour": 10,
        "Smoothness": 25
    },
    {
        "Picture": "/berries/leppa.png",
        "Name": "Leppa Berry",
        "Firmness": "Very Hard",
        "Description": "It takes longer to grow than Berries such as Cheri. The smaller Berries taste better.",
        "Spicy": 10,
        "Dry": 0,
        "Sweet": 10,
        "Bitter": 10,
        "Sour": 10,
        "Smoothness": 20
    },
    {
        "Picture": "/berries/oran.png",
        "Name": "Oran Berry",
        "Firmness": "Super Hard",
        "Description": "Nature's gifts came together as one in this Berry. It has a wondrous mix of flavors that spread in the mouth.",
        "Spicy": 10,
        "Dry": 10,
        "Sweet": 0,
        "Bitter": 10,
        "Sour": 10,
        "Smoothness": 20
    },
    {
        "Picture": "/berries/persim.png",
        "Name": "Persim Berry",
        "Firmness": "Hard",
        "Description": "The more this Berry absorbs energy from sunlight, the more vividly colorful it grows.",
        "Spicy": 10,
        "Dry": 10,
        "Sweet": 10,
        "Bitter": 0,
        "Sour": 10,
        "Smoothness": 20
    },
    {
        "Picture": "/berries/lum.png",
        "Name": "Lum Berry",
        "Firmness": "Super Hard",
        "Description": "This Berry's gradual process of storing nutrients beneficial to Pokémon health causes it to mature slowly.",
        "Spicy": 10,
        "Dry": 10,
        "Sweet": 10,
        "Bitter": 10,
        "Sour": 0,
        "Smoothness": 20
    },
    {
        "Picture": "/berries/sitrus.png",
        "Name": "Sitrus Berry",
        "Firmness": "Very Hard",
        "Description": "Sitrus came from the same family as Oran. It is larger and smoother-tasting than Oran.",
        "Spicy": 0,
        "Dry": 10,
        "Sweet": 10,
        "Bitter": 10,
        "Sour": 10,
        "Smoothness": 20
    },
    {
        "Picture": "/berries/figy.png",
        "Name": "Figy Berry",
        "Firmness": "Soft",
        "Description": "This Berry is oddly shaped, appearing as if someone took a bite out of it. It is packed full of spicy substances.",
        "Spicy": 15,
        "Dry": 0,
        "Sweet": 0,
        "Bitter": 0,
        "Sour": 0,
        "Smoothness": 25
    },
    {
        "Picture": "/berries/wiki.png",
        "Name": "Wiki Berry",
        "Firmness": "Hard",
        "Description": "It is said that this Berry grew lumps to help Pokémon grip it, allowing propagation farther afield.",
        "Spicy": 0,
        "Dry": 15,
        "Sweet": 0,
        "Bitter": 0,
        "Sour": 0,
        "Smoothness": 25
    },
    {
        "Picture": "/berries/mago.png",
        "Name": "Mago Berry",
        "Firmness": "Hard",
        "Description": "This Berry progressively curves as it grows. The curvier the Berry, the sweeter it tastes.",
        "Spicy": 0,
        "Dry": 0,
        "Sweet": 15,
        "Bitter": 0,
        "Sour": 0,
        "Smoothness": 25
    },
    {
        "Picture": "/berries/aguav.png",
        "Name": "Aguav Berry",
        "Firmness": "Super Hard",
        "Description": "This Berry turns bitter toward the stem. The dainty flower it grows from doesn't absorb much sunlight.",
        "Spicy": 0,
        "Dry": 0,
        "Sweet": 0,
        "Bitter": 15,
        "Sour": 0,
        "Smoothness": 25
    },
    {
        "Picture": "/berries/iapapa.png",
        "Name": "Iapapa Berry",
        "Firmness": "Soft",
        "Description": "This Berry is very big and sour. The juiciness of the pulp accentuates the sourness.",
        "Spicy": 0,
        "Dry": 0,
        "Sweet": 0,
        "Bitter": 0,
        "Sour": 15,
        "Smoothness": 25
    },
    {
        "Picture": "/berries/razz.png",
        "Name": "Razz Berry",
        "Firmness": "Very Hard",
        "Description": "A small hint of spiciness lingers in the red granules surrounding this Berry. Their centers have a dry taste.",
        "Spicy": 10,
        "Dry": 10,
        "Sweet": 0,
        "Bitter": 0,
        "Sour": 0,
        "Smoothness": 20
    },
    {
        "Picture": "/berries/bluk.png",
        "Name": "Bluk Berry",
        "Firmness": "Soft",
        "Description": "Though this small, delicately skinned Berry is blue in color, it dyes the mouth black when eaten.",
        "Spicy": 0,
        "Dry": 10,
        "Sweet": 10,
        "Bitter": 0,
        "Sour": 0,
        "Smoothness": 20
    },
    {
        "Picture": "/berries/nanab.png",
        "Name": "Nanab Berry",
        "Firmness": "Very Hard",
        "Description": "Bitter, but with a trace of sweetness, the Nanab Berry was the seventh to be discovered in the world.",
        "Spicy": 0,
        "Dry": 0,
        "Sweet": 10,
        "Bitter": 10,
        "Sour": 0,
        "Smoothness": 20
    },
    {
        "Picture": "/berries/wepear.png",
        "Name": "Wepear Berry",
        "Firmness": "Super Hard",
        "Description": "The potent mix of bitter and sour in this Berry seems to promote digestion. The flower is white and beautiful.",
        "Spicy": 0,
        "Dry": 0,
        "Sweet": 0,
        "Bitter": 10,
        "Sour": 10,
        "Smoothness": 20
    },
    {
        "Picture": "/berries/pinap.png",
        "Name": "Pinap Berry",
        "Firmness": "Hard",
        "Description": "It is said that when the sour skin is peeled, this spicy Berry can be crushed to make medicine.",
        "Spicy": 10,
        "Dry": 0,
        "Sweet": 0,
        "Bitter": 0,
        "Sour": 10,
        "Smoothness": 20
    },
    {
        "Picture": "/berries/pomeg.png",
        "Name": "Pomeg Berry",
        "Firmness": "Very Hard",
        "Description": "When this sweetly spicy Berry's thick skin is peeled, many pieces of the fruit spill out.",
        "Spicy": 10,
        "Dry": 0,
        "Sweet": 10,
        "Bitter": 10,
        "Sour": 0,
        "Smoothness": 20
    },
    {
        "Picture": "/berries/kelpsy.png",
        "Name": "Kelpsy Berry",
        "Firmness": "Hard",
        "Description": "This Berry can be eaten as is or boiled to obtain an extract that adds a dash of flavor to food.",
        "Spicy": 0,
        "Dry": 10,
        "Sweet": 0,
        "Bitter": 10,
        "Sour": 10,
        "Smoothness": 20
    },
    {
        "Picture": "/berries/qualot.png",
        "Name": "Qualot Berry",
        "Firmness": "Hard",
        "Description": "Even in places of constant rain and high humidity, this Berry's plant grows healthy and strong.",
        "Spicy": 10,
        "Dry": 0,
        "Sweet": 10,
        "Bitter": 0,
        "Sour": 10,
        "Smoothness": 20
    },
    {
        "Picture": "/berries/hondew.png",
        "Name": "Hondew Berry",
        "Firmness": "Hard",
        "Description": "This somewhat-rare Berry projects an image of luxury, so it is favored as a gift item.",
        "Spicy": 10,
        "Dry": 10,
        "Sweet": 0,
        "Bitter": 10,
        "Sour": 0,
        "Smoothness": 20
    },
    {
        "Picture": "/berries/grepa.png",
        "Name": "Grepa Berry",
        "Firmness": "Soft",
        "Description": "One bite of this very tender Berry fills the mouth with its sweet and tangy flavor.",
        "Spicy": 0,
        "Dry": 10,
        "Sweet": 10,
        "Bitter": 0,
        "Sour": 10,
        "Smoothness": 20
    },
    {
        "Picture": "/berries/tamato.png",
        "Name": "Tamato Berry",
        "Firmness": "Soft",
        "Description": "This Berry is large and spicy. When eaten during the cold season, it warms the body from inside.",
        "Spicy": 20,
        "Dry": 10,
        "Sweet": 0,
        "Bitter": 0,
        "Sour": 0,
        "Smoothness": 30
    },
    {
        "Picture": "/berries/cornn.png",
        "Name": "Cornn Berry",
        "Firmness": "Hard",
        "Description": "Its dryness is quite strong. As a result, its true deliciousness can't be appreciated by just eating one or two.",
        "Spicy": 0,
        "Dry": 20,
        "Sweet": 10,
        "Bitter": 0,
        "Sour": 0,
        "Smoothness": 30
    },
    {
        "Picture": "/berries/magost.png",
        "Name": "Magost Berry",
        "Firmness": "Hard",
        "Description": "The grown-up flavor and dreamy sweetness of this Berry make it a favorite of Pokémon everywhere.",
        "Spicy": 0,
        "Dry": 0,
        "Sweet": 20,
        "Bitter": 10,
        "Sour": 0,
        "Smoothness": 30
    },
    {
        "Picture": "/berries/rabuta.png",
        "Name": "Rabuta Berry",
        "Firmness": "Soft",
        "Description": "Even though this Berry is bitter, it should be eaten peel and all. The hair on the peel cleans the stomach from the inside.",
        "Spicy": 0,
        "Dry": 0,
        "Sweet": 0,
        "Bitter": 20,
        "Sour": 10,
        "Smoothness": 30
    },
    {
        "Picture": "/berries/nomel.png",
        "Name": "Nomel Berry",
        "Firmness": "Super Hard",
        "Description": "This Berry is quite sour overall, with the sourness especially concentrated at the pointed end.",
        "Spicy": 10,
        "Dry": 0,
        "Sweet": 0,
        "Bitter": 0,
        "Sour": 20,
        "Smoothness": 30
    },
    {
        "Picture": "/berries/spelon.png",
        "Name": "Spelon Berry",
        "Firmness": "Soft",
        "Description": "So spicy is the Spelon Berry that, Fire type or not, Pokémon will try to breathe fire after eating a single one.",
        "Spicy": 30,
        "Dry": 10,
        "Sweet": 0,
        "Bitter": 0,
        "Sour": 0,
        "Smoothness": 35
    },
    {
        "Picture": "/berries/pamtre.png",
        "Name": "Pamtre Berry",
        "Firmness": "Very Soft",
        "Description": "This Berry drifted from a faraway sea. It is now cultivated in the Sinnoh region.",
        "Spicy": 0,
        "Dry": 30,
        "Sweet": 10,
        "Bitter": 0,
        "Sour": 0,
        "Smoothness": 35
    },
    {
        "Picture": "/berries/watmel.png",
        "Name": "Watmel Berry",
        "Firmness": "Soft",
        "Description": "A bounty of nature that is exceedingly sweet. The Berry is huge, with some discovered that exceed 20 inches.",
        "Spicy": 0,
        "Dry": 0,
        "Sweet": 30,
        "Bitter": 10,
        "Sour": 0,
        "Smoothness": 35
    },
    {
        "Picture": "/berries/durin.png",
        "Name": "Durin Berry",
        "Firmness": "Hard",
        "Description": "This Berry is tremendously bitter. Just one bite is enough to instantly stop hiccups.",
        "Spicy": 0,
        "Dry": 0,
        "Sweet": 0,
        "Bitter": 30,
        "Sour": 10,
        "Smoothness": 35
    },
    {
        "Picture": "/berries/belue.png",
        "Name": "Belue Berry",
        "Firmness": "Very Soft",
        "Description": "This glossy and colorful Berry has a mouthwateringly delicious appearance. However, it is awfully sour.",
        "Spicy": 10,
        "Dry": 0,
        "Sweet": 0,
        "Bitter": 0,
        "Sour": 30,
        "Smoothness": 35
    },
    {
        "Picture": "/berries/occa.png",
        "Name": "Occa Berry",
        "Firmness": "Super Hard",
        "Description": "This Berry is said to have grown plentiful in the tropics of the past. It boasts an intensely hot spiciness.",
        "Spicy": 15,
        "Dry": 0,
        "Sweet": 10,
        "Bitter": 0,
        "Sour": 0,
        "Smoothness": 30
    },
    {
        "Picture": "/berries/passho.png",
        "Name": "Passho Berry",
        "Firmness": "Soft",
        "Description": "This Berry's flesh is dotted with countless tiny bubbles of air that keep it afloat in water.",
        "Spicy": 0,
        "Dry": 15,
        "Sweet": 0,
        "Bitter": 10,
        "Sour": 0,
        "Smoothness": 30
    },
    {
        "Picture": "/berries/wacan.png",
        "Name": "Wacan Berry",
        "Firmness": "Very Soft",
        "Description": "Energy from lightning strikes is drawn into the plant, making the Berries grow big and rich.",
        "Spicy": 0,
        "Dry": 0,
        "Sweet": 15,
        "Bitter": 0,
        "Sour": 10,
        "Smoothness": 30
    },
    {
        "Picture": "/berries/rindo.png",
        "Name": "Rindo Berry",
        "Firmness": "Soft",
        "Description": "This Berry has a disagreeable âgreenâ flavor and scent typical of vegetables. It is rich in health-promoting fiber.",
        "Spicy": 10,
        "Dry": 0,
        "Sweet": 0,
        "Bitter": 15,
        "Sour": 0,
        "Smoothness": 30
    },
    {
        "Picture": "/berries/yache.png",
        "Name": "Yache Berry",
        "Firmness": "Very Hard",
        "Description": "This Berry has a refreshing flavor that strikes a good balance of dryness and sourness. It tastes better chilled.",
        "Spicy": 0,
        "Dry": 10,
        "Sweet": 0,
        "Bitter": 0,
        "Sour": 15,
        "Smoothness": 30
    },
    {
        "Picture": "/berries/chople.png",
        "Name": "Chople Berry",
        "Firmness": "Soft",
        "Description": "This Berry contains a substance that generates heat. It can even heat up a chilly heart.",
        "Spicy": 15,
        "Dry": 0,
        "Sweet": 0,
        "Bitter": 10,
        "Sour": 0,
        "Smoothness": 30
    },
    {
        "Picture": "/berries/kebia.png",
        "Name": "Kebia Berry",
        "Firmness": "Hard",
        "Description": "This Berry is a brilliant green on the outside. Inside, it is packed with a dry-flavored, black-colored flesh.",
        "Spicy": 0,
        "Dry": 15,
        "Sweet": 0,
        "Bitter": 0,
        "Sour": 10,
        "Smoothness": 30
    },
    {
        "Picture": "/berries/shuca.png",
        "Name": "Shuca Berry",
        "Firmness": "Soft",
        "Description": "The sweetness-laden pulp has just the hint of a hard-edged and fragrant bite to it.",
        "Spicy": 10,
        "Dry": 0,
        "Sweet": 15,
        "Bitter": 0,
        "Sour": 0,
        "Smoothness": 30
    },
    {
        "Picture": "/berries/coba.png",
        "Name": "Coba Berry",
        "Firmness": "Very Hard",
        "Description": "This Berry is said to be a new kind that is a cross of two Berries brought together by winds from far away.",
        "Spicy": 0,
        "Dry": 10,
        "Sweet": 0,
        "Bitter": 15,
        "Sour": 0,
        "Smoothness": 30
    },
    {
        "Picture": "/berries/payapa.png",
        "Name": "Payapa Berry",
        "Firmness": "Soft",
        "Description": "This Berry is said to sense human emotions for the way it swells roundly when a person approaches.",
        "Spicy": 0,
        "Dry": 0,
        "Sweet": 10,
        "Bitter": 0,
        "Sour": 15,
        "Smoothness": 30
    },
    {
        "Picture": "/berries/tanga.png",
        "Name": "Tanga Berry",
        "Firmness": "Very Soft",
        "Description": "The flower grows at the tip of this Berry. It attracts Bug Pokémon by letting its stringy petals stream out.",
        "Spicy": 20,
        "Dry": 0,
        "Sweet": 0,
        "Bitter": 0,
        "Sour": 10,
        "Smoothness": 35
    },
    {
        "Picture": "/berries/charti.png",
        "Name": "Charti Berry",
        "Firmness": "Very Soft",
        "Description": "It is often used for pickles because of its very dry flavor. It can also be eaten raw for its provocative taste.",
        "Spicy": 10,
        "Dry": 20,
        "Sweet": 0,
        "Bitter": 0,
        "Sour": 0,
        "Smoothness": 35
    },
    {
        "Picture": "/berries/kasib.png",
        "Name": "Kasib Berry",
        "Firmness": "Hard",
        "Description": "Considered to have a special power from the olden days, this Berry is sometimes dried and used as a good luck charm.",
        "Spicy": 0,
        "Dry": 10,
        "Sweet": 20,
        "Bitter": 0,
        "Sour": 0,
        "Smoothness": 35
    },
    {
        "Picture": "/berries/haban.png",
        "Name": "Haban Berry",
        "Firmness": "Soft",
        "Description": "If a large enough volume of this Berry is boiled down, its bitterness fades away. It makes a good jam.",
        "Spicy": 0,
        "Dry": 0,
        "Sweet": 10,
        "Bitter": 20,
        "Sour": 0,
        "Smoothness": 35
    },
    {
        "Picture": "/berries/colbur.png",
        "Name": "Colbur Berry",
        "Firmness": "Super Hard",
        "Description": "Tiny hooks grow on the surface of this Berry. It latches on to Pokémon so it can be carried to far-off places.",
        "Spicy": 0,
        "Dry": 0,
        "Sweet": 0,
        "Bitter": 10,
        "Sour": 20,
        "Smoothness": 35
    },
    {
        "Picture": "/berries/babiri.png",
        "Name": "Babiri Berry",
        "Firmness": "Super Hard",
        "Description": "This Berry is very tough with a strong flavor. It was used to make medicine by people in the past.",
        "Spicy": 25,
        "Dry": 10,
        "Sweet": 0,
        "Bitter": 0,
        "Sour": 0,
        "Smoothness": 35
    },
    {
        "Picture": "/berries/chilan.png",
        "Name": "Chilan Berry",
        "Firmness": "Very Soft",
        "Description": "This Berry can be cored out and dried to make a whistle. Blowing through its hole makes an indescribable sound.",
        "Spicy": 0,
        "Dry": 25,
        "Sweet": 10,
        "Bitter": 0,
        "Sour": 0,
        "Smoothness": 35
    },
    {
        "Picture": "/berries/liechi.png",
        "Name": "Liechi Berry",
        "Firmness": "Very Hard",
        "Description": "This Berry is surrounded by mystery. It is rumored to be imbued with the power of the sea.",
        "Spicy": 30,
        "Dry": 10,
        "Sweet": 30,
        "Bitter": 0,
        "Sour": 0,
        "Smoothness": 40
    },
    {
        "Picture": "/berries/ganlon.png",
        "Name": "Ganlon Berry",
        "Firmness": "Very Hard",
        "Description": "This Berry is surrounded by mystery. It is rumored to be imbued with the power of the land.",
        "Spicy": 0,
        "Dry": 30,
        "Sweet": 10,
        "Bitter": 30,
        "Sour": 0,
        "Smoothness": 40
    },
    {
        "Picture": "/berries/salac.png",
        "Name": "Salac Berry",
        "Firmness": "Very Hard",
        "Description": "This Berry is surrounded by mystery. It is rumored to be imbued with the power of the sky.",
        "Spicy": 0,
        "Dry": 0,
        "Sweet": 30,
        "Bitter": 10,
        "Sour": 30,
        "Smoothness": 40
    },
    {
        "Picture": "/berries/petaya.png",
        "Name": "Petaya Berry",
        "Firmness": "Very Hard",
        "Description": "This Berry is surrounded by mystery. It is rumored to be imbued with the power of all living things.",
        "Spicy": 30,
        "Dry": 0,
        "Sweet": 0,
        "Bitter": 30,
        "Sour": 10,
        "Smoothness": 40
    },
    {
        "Picture": "/berries/apicot.png",
        "Name": "Apicot Berry",
        "Firmness": "Hard",
        "Description": "This is a very, very mystifying Berry. There is no telling how it can be used, or what may happen if it is used.",
        "Spicy": 10,
        "Dry": 30,
        "Sweet": 0,
        "Bitter": 0,
        "Sour": 30,
        "Smoothness": 40
    },
    {
        "Picture": "/berries/lansat.png",
        "Name": "Lansat Berry",
        "Firmness": "Soft",
        "Description": "This is said to be a legendary Berry. Holding it supposedly brings great joy.",
        "Spicy": 30,
        "Dry": 10,
        "Sweet": 30,
        "Bitter": 10,
        "Sour": 30,
        "Smoothness": 50
    },
    {
        "Picture": "/berries/starf.png",
        "Name": "Starf Berry",
        "Firmness": "Super Hard",
        "Description": "This Berry is considered a mirage. It was said to be so strong that it had to be abandoned at the world's edge.",
        "Spicy": 30,
        "Dry": 10,
        "Sweet": 30,
        "Bitter": 10,
        "Sour": 30,
        "Smoothness": 50
    },
    {
        "Picture": "/berries/enigma.png",
        "Name": "Enigma Berry",
        "Firmness": "Hard",
        "Description": "A completely enigmatic Berry. It apparently has the power of the stars that fill the night sky.",
        "Spicy": 40,
        "Dry": 10,
        "Sweet": 0,
        "Bitter": 0,
        "Sour": 0,
        "Smoothness": 60
    },
    {
        "Picture": "/berries/micle.png",
        "Name": "Micle Berry",
        "Firmness": "Soft",
        "Description": "This Berry has a very dry flavor. It has the effect of making other food eaten at the same time taste sweet.",
        "Spicy": 0,
        "Dry": 40,
        "Sweet": 10,
        "Bitter": 0,
        "Sour": 0,
        "Smoothness": 60
    },
    {
        "Picture": "/berries/custap.png",
        "Name": "Custap Berry",
        "Firmness": "Super Hard",
        "Description": "The flesh underneath the Custap Berry's tough skin is sweet and creamy soft.",
        "Spicy": 0,
        "Dry": 0,
        "Sweet": 40,
        "Bitter": 10,
        "Sour": 0,
        "Smoothness": 60
    },
    {
        "Picture": "/berries/jaboca.png",
        "Name": "Jaboca Berry",
        "Firmness": "Soft",
        "Description": "The cluster of drupelets that make up this Berry pop rhythmically if the Berry is handled roughly.",
        "Spicy": 0,
        "Dry": 0,
        "Sweet": 0,
        "Bitter": 40,
        "Sour": 10,
        "Smoothness": 60
    },
    {
        "Picture": "/berries/rowap.png",
        "Name": "Rowap Berry",
        "Firmness": "Very Soft",
        "Description": "In days of old, people worked the top-shaped pieces of this Berry free and used them as toys.",
        "Spicy": 10,
        "Dry": 0,
        "Sweet": 0,
        "Bitter": 0,
        "Sour": 40,
        "Smoothness": 60
    },
    {
        "Picture": "/berries/roseli.png",
        "Name": "Roseli Berry",
        "Firmness": "Hard",
        "Description": "The slight bitterness that cuts through the rich sweetness makes this Berry a perfect ingredient for adding an accent.",
        "Spicy": 0,
        "Dry": 0,
        "Sweet": 25,
        "Bitter": 10,
        "Sour": 0,
        "Smoothness": 35
    }
]